pypnusershub/__init__.py
pypnusershub/__main__.py
pypnusershub/commands.py
pypnusershub/decorators.py
pypnusershub/env.py
pypnusershub/login_manager.py
pypnusershub/routes.py
pypnusershub/schemas.py
pypnusershub/test_settings.py
pypnusershub/utils.py
pypnusershub/auth/__init__.py
pypnusershub/auth/auth_manager.py
pypnusershub/auth/authentication.py
pypnusershub/auth/subscribe.py
pypnusershub/auth/providers/__init__.py
pypnusershub/auth/providers/cas_inpn_provider.py
pypnusershub/auth/providers/default.py
pypnusershub/auth/providers/openid_provider.py
pypnusershub/auth/providers/usershub_provider.py
pypnusershub/db/__init__.py
pypnusershub/db/models.py
pypnusershub/db/models_register.py
pypnusershub/db/tools.py
pypnusershub/migrations/__init__.py
pypnusershub/migrations/env.py
pypnusershub/migrations/data/__init__.py
pypnusershub/migrations/data/utilisateurs-samples.sql
pypnusershub/migrations/data/utilisateurs.sql
pypnusershub/migrations/versions/10e87bc144cd_get_id_role_by_name.py
pypnusershub/migrations/versions/112ccf1024ce_add_unique_constraint_on_t_roles_uuid.py
pypnusershub/migrations/versions/5b334b77f5f5_fix_v_roleslist_forall_applications.py
pypnusershub/migrations/versions/72f227e37bdf_utilisateurs_sample_data.py
pypnusershub/migrations/versions/830cc8f4daef_add_additional_data_field_to_organism.py
pypnusershub/migrations/versions/951b8270a1cf_add_unique_constraint_on_uuid_organisme.py
pypnusershub/migrations/versions/__init__.py
pypnusershub/migrations/versions/b3dec57f13d8_add_drop_on_cascade_on_cor_role_.py
pypnusershub/migrations/versions/b7c98935d9e8_add_providers_table_and_cor_tables_with_troles.py
pypnusershub/migrations/versions/cf38131bc247_add_meta_create_insert_date_to_.py
pypnusershub/migrations/versions/f4bf21ac6238_fix_temp_user_organism_size.py
pypnusershub/migrations/versions/f9d3b95946cd_set_code_profil_in_integer.py
pypnusershub/migrations/versions/fa35dfe5ff27_create_utilisateurs_schema.py
pypnusershub/tests/__init__.py
pypnusershub-3.1.0.dist-info/licenses/LICENSE
pypnusershub-3.1.0.dist-info/METADATA
pypnusershub-3.1.0.dist-info/WHEEL
pypnusershub-3.1.0.dist-info/entry_points.txt
pypnusershub-3.1.0.dist-info/top_level.txt
pypnusershub-3.1.0.dist-info/RECORD
