Metadata-Version: 2.4
Name: pypnusershub
Version: 3.1.0
Summary: Python lib to authenticate using PN's UsersHub
Home-page: https://github.com/PnX-SI/UsersHub-authentification-module
Maintainer: Parcs nationaux des Écrins et des Cévennes
Maintainer-email: geonature@ecrins-parcnational.fr
Classifier: Development Status :: 1 - Planning
Classifier: Intended Audience :: Developers
Classifier: Natural Language :: English
Classifier: Programming Language :: Python :: 3
Classifier: Programming Language :: Python :: 3.9
Classifier: Programming Language :: Python :: 3.11
Classifier: License :: OSI Approved :: GNU Affero General Public License v3
Classifier: Operating System :: OS Independent
License-File: LICENSE
Requires-Dist: authlib
Requires-Dist: bcrypt
Requires-Dist: flask-sqlalchemy
Requires-Dist: flask>=3
Requires-Dist: flask-login
Requires-Dist: psycopg2
Requires-Dist: requests
Requires-Dist: sqlalchemy<2,>=1.4
Requires-Dist: flask-marshmallow
Requires-Dist: marshmallow-sqlalchemy
Requires-Dist: alembic
Requires-Dist: xmltodict
Requires-Dist: utils-flask-sqlalchemy<1.0,>=0.4.1
Provides-Extra: tests
Requires-Dist: pytest; extra == "tests"
Requires-Dist: pytest-flask; extra == "tests"
Dynamic: classifier
Dynamic: description
Dynamic: description-content-type
Dynamic: home-page
Dynamic: license-file
Dynamic: maintainer
Dynamic: maintainer-email
Dynamic: provides-extra
Dynamic: requires-dist
Dynamic: summary
